mypackage_prince_boom/__init__.py
mypackage_prince_boom-0.0.5.dist-info/LICENSE
mypackage_prince_boom-0.0.5.dist-info/METADATA
mypackage_prince_boom-0.0.5.dist-info/WHEEL
mypackage_prince_boom-0.0.5.dist-info/entry_points.txt
mypackage_prince_boom-0.0.5.dist-info/top_level.txt
mypackage_prince_boom-0.0.5.dist-info/RECORD
