Metadata-Version: 2.1
Name: mypackage-prince-boom
Version: 0.0.5
Summary: A short description of your package
Home-page: https://github.com/prince7417/mypackage_prince_boom
Author: prince
Author-email: princee.studio45creations@gmail.com
License: UNKNOWN
Platform: UNKNOWN
Classifier: Programming Language :: Python :: 3
Classifier: License :: OSI Approved :: MIT License
Classifier: Operating System :: OS Independent
License-File: LICENSE
Requires-Dist: requests
